debrepomanager/__init__.py
debrepomanager/aptly.py
debrepomanager/cli.py
debrepomanager/config.py
debrepomanager/gpg.py
debrepomanager/gpg_rotation.py
debrepomanager/metadata.py
debrepomanager/retention.py
debrepomanager/utils.py
debrepomanager-0.3.6.dist-info/licenses/LICENSE
debrepomanager-0.3.6.dist-info/METADATA
debrepomanager-0.3.6.dist-info/WHEEL
debrepomanager-0.3.6.dist-info/entry_points.txt
debrepomanager-0.3.6.dist-info/top_level.txt
debrepomanager-0.3.6.dist-info/RECORD
