Metadata-Version: 2.4
Name: debrepomanager
Version: 0.3.6
Summary: Debian Repository Manager for multi-distribution package management
Home-page: https://github.com/jethome/repomanager
Author: Viacheslav Bocharov
Author-email: Viacheslav Bocharov <vb@jethome.com>
License: MIT
Project-URL: Homepage, https://github.com/jethome/repomanager
Project-URL: Documentation, https://github.com/jethome/repomanager/blob/main/README.md
Project-URL: Repository, https://github.com/jethome/repomanager.git
Project-URL: Issues, https://github.com/jethome/repomanager/issues
Keywords: debian,repository,apt,aptly,package-management
Classifier: Development Status :: 3 - Alpha
Classifier: Intended Audience :: System Administrators
Classifier: Intended Audience :: Developers
Classifier: License :: OSI Approved :: MIT License
Classifier: Operating System :: POSIX :: Linux
Classifier: Programming Language :: Python :: 3
Classifier: Programming Language :: Python :: 3.11
Classifier: Programming Language :: Python :: 3.12
Classifier: Programming Language :: Python :: 3.13
Classifier: Topic :: System :: Software Distribution
Classifier: Topic :: System :: Systems Administration
Requires-Python: >=3.11
License-File: LICENSE
Requires-Dist: PyYAML>=6.0
Requires-Dist: click>=8.0.0
Requires-Dist: python-debian>=0.1.49
Requires-Dist: python-dateutil>=2.8.0
Provides-Extra: dev
Requires-Dist: pytest>=7.0.0; extra == "dev"
Requires-Dist: pytest-cov>=4.0.0; extra == "dev"
Requires-Dist: pytest-mock>=3.10.0; extra == "dev"
Requires-Dist: pytest-timeout>=2.0.0; extra == "dev"
Requires-Dist: hypothesis>=6.0.0; extra == "dev"
Requires-Dist: black>=23.0.0; extra == "dev"
Requires-Dist: flake8>=6.0.0; extra == "dev"
Requires-Dist: mypy>=1.0.0; extra == "dev"
Requires-Dist: isort>=5.0.0; extra == "dev"
Requires-Dist: types-PyYAML>=6.0.0; extra == "dev"
Requires-Dist: types-python-dateutil>=2.8.0; extra == "dev"
Dynamic: author
Dynamic: home-page
Dynamic: license-file
Dynamic: requires-python
